LICENSE.txt
README.md
setup.py
espsim/QM_137k.pt
espsim/__init__.py
espsim/electrostatics.py
espsim/helpers.py
espsim.egg-info/PKG-INFO
espsim.egg-info/SOURCES.txt
espsim.egg-info/dependency_links.txt
espsim.egg-info/top_level.txt