Metadata-Version: 2.1
Name: espsim
Version: 0.0.1
Summary: Scoring of shape and ESP similarity with RDKit
Home-page: https://github.com/hesther/espsim
Author: Esther Heid
Author-email: eheid@mit.edu
License: MIT
Keywords: chemistry,electrostatic potential,shape,similarity,RDKit
Platform: UNKNOWN
Classifier: Programming Language :: Python :: 3
Classifier: License :: OSI Approved :: MIT License
Classifier: Operating System :: OS Independent
License-File: LICENSE.txt
